numerous/declarative/context_managers.py
numerous/declarative/debug_utils.py
numerous/declarative/enums.py
numerous/declarative/equations.py
numerous/declarative/exceptions.py
numerous/declarative/generator.py
numerous/declarative/instance.py
numerous/declarative/mappings.py
numerous/declarative/signal.py
numerous/declarative/utils.py
numerous/declarative/connectors/connection.py
numerous/declarative/connectors/create_connections.py
numerous/declarative/connectors/declarativeconnector.py
numerous/declarative/connectors/module_connections.py
numerous/declarative/specifications/equation_spec.py
numerous/declarative/specifications/interfaces.py
numerous/declarative/specifications/item_spec.py
numerous/declarative/specifications/module.py
numerous/declarative/specifications/module_spec.py
numerous/declarative/specifications/scope_spec.py
numerous/declarative/variables/declarative_variables.py
numerous/engine/__init__.py
numerous/engine/numerous_event.py
numerous/engine/variables.py
numerous/engine/model/__init__.py
numerous/engine/model/aliased_dataframe.py
numerous/engine/model/compiled_model.py
numerous/engine/model/events.py
numerous/engine/model/model.py
numerous/engine/model/utils.py
numerous/engine/model/ast_parser/__init__.py
numerous/engine/model/ast_parser/ast_visitor.py
numerous/engine/model/ast_parser/equation_from_graph.py
numerous/engine/model/ast_parser/parser_ast.py
numerous/engine/model/graph_representation/__init__.py
numerous/engine/model/graph_representation/graph.py
numerous/engine/model/graph_representation/lower_graph.py
numerous/engine/model/graph_representation/mappings_graph.py
numerous/engine/model/graph_representation/utils.py
numerous/engine/model/lowering/__init__.py
numerous/engine/model/lowering/ast_builder.py
numerous/engine/model/lowering/equations_generator.py
numerous/engine/model/lowering/llvm_builder.py
numerous/engine/model/lowering/llvm_initializer.py
numerous/engine/model/lowering/utils.py
numerous/engine/simulation/__init__.py
numerous_engine-0.5.2.dist-info/LICENSE.txt
numerous_engine-0.5.2.dist-info/METADATA
numerous_engine-0.5.2.dist-info/WHEEL
numerous_engine-0.5.2.dist-info/top_level.txt
numerous_engine-0.5.2.dist-info/RECORD
