Metadata-Version: 2.1
Name: numerous-engine
Version: 0.5.2
Summary: Numerous  - an object-oriented modelling and simulation engine.
Home-page: https://github.com/fossilfree/numerous
Author: Artem Chupryna, EnergyMachines ApS
Author-email: artem.chupryna@energymachines.com
Classifier: Programming Language :: Python :: 3
Classifier: License :: OSI Approved :: BSD License
Classifier: Operating System :: OS Independent
Requires-Python: >=3.11
License-File: LICENSE.txt
Requires-Dist: attrs (>=19.3.0)
Requires-Dist: deprecation (==2.1.0)
Requires-Dist: fmpy (==0.3.7)
Requires-Dist: graphviz
Requires-Dist: importlib-metadata (>=1.3.0)
Requires-Dist: more-itertools (>=8.0.2)
Requires-Dist: networkx (>=2.4)
Requires-Dist: numba (==0.57.0)
Requires-Dist: numerous-solver (>=2.2.3)
Requires-Dist: numpy (>=1.24.3)
Requires-Dist: packaging (>=19.2)
Requires-Dist: pandas (>=1.0.5)
Requires-Dist: py (>=1.11)
Requires-Dist: pyparsing (>=2.4.5)
Requires-Dist: pytest (>=5.3.1)
Requires-Dist: python-dateutil (>=2.8.1)
Requires-Dist: pytz (>=2019.3)
Requires-Dist: six (>=1.13.0)
Requires-Dist: tqdm (>=4.40.2)
Requires-Dist: wcwidth (>=0.1.7)
Requires-Dist: zipp (>=0.6.0)
